[
	{
		"id":"1",
		"img":"1.jpg",
		"share":"分享",
		"collect":"收藏",
		"info":"消费者告知书",
		"h1":"[中国 · 气质韩范变身女主]WRZS 小清新学院风假两件蕾丝蛋糕裙中长款半身裙图片色(均码)",
		"goods":"达令价",
		"f1":"￥",
		"f30":"89.90",
		"p":"海外现时售价",
		"jia":"¥288.00",
		"off":"3.1折",
		"coll":"收藏",
		"count":"53",
		"num":"购买数量",
		"buy":"立即购买",
		"cart":"添加到购物车",
		"mark1":"正品保障",
		"mark2":"24小时发货",
		"mark3":"满55元快递包邮",
		"zi":"商品信息",
		"img1":"2.jpg",
		"img2":"3.jpg",
		"img3":"4.jpg",
		"img4":"5.jpg",
		"img5":"6.jpg",
		"img6":"7.jpg",
		"img7":"8.jpg",
		"img8":"9.jpg",
		"img9":"1.jpg"		
	}
]
